turn_ephemeral_credentials/__init__.py
turn_ephemeral_credentials-1.0.1.dist-info/LICENSE
turn_ephemeral_credentials-1.0.1.dist-info/METADATA
turn_ephemeral_credentials-1.0.1.dist-info/WHEEL
turn_ephemeral_credentials-1.0.1.dist-info/top_level.txt
turn_ephemeral_credentials-1.0.1.dist-info/RECORD
