Metadata-Version: 2.1
Name: turn-ephemeral-credentials
Version: 1.0.1
Summary: Generate time limited, ephemeral, long term credentials to authenticate usage of a turn server.
Author-email: p4irin <139928764+p4irin@users.noreply.github.com>
License: MIT License
Project-URL: Homepage, https://github.com/p4irin/turn_ephemeral_credentials
Project-URL: Bug Tracker, https://github.com/p4irin/turn_ephemeral_credentials/issues
Keywords: turn,stun,ice
Classifier: Programming Language :: Python :: 3
Classifier: Programming Language :: Python :: 3.8
Classifier: Operating System :: POSIX :: Linux
Classifier: Intended Audience :: Developers
Classifier: Intended Audience :: Telecommunications Industry
Classifier: Topic :: Communications :: Internet Phone
Classifier: Topic :: Software Development :: Libraries :: Python Modules
Classifier: License :: OSI Approved :: MIT License
Requires-Python: >=3.8.10
License-File: LICENSE
Provides-Extra: dev
Requires-Dist: build ==0.10.0 ; extra == 'dev'
Requires-Dist: twine >=4.0.2 ; extra == 'dev'
Requires-Dist: bumpver >=2023.1126 ; extra == 'dev'
